setup.py
django_kaskader.egg-info/PKG-INFO
django_kaskader.egg-info/SOURCES.txt
django_kaskader.egg-info/dependency_links.txt
django_kaskader.egg-info/top_level.txt
kaskader/__init__.py
kaskader/tests/__init__.py
kaskader/tests/generators.py
kaskader/tests/missing_tests.py
kaskader/tests/mixins.py
kaskader/tests/runners.py